gmms/CampbellBozorgnia2010.py
gmms/CampbellBozorgnia2010_cy.c
gmms/CampbellBozorgnia2010_cy.cp312-win_amd64.pyd
gmms/CampbellBozorgnia2010_cy.pyx
gmms/CampbellBozorgnia2010_py.py
gmms/CampbellBozorgnia2011.py
gmms/CampbellBozorgnia2011_cy.c
gmms/CampbellBozorgnia2011_cy.cp312-win_amd64.pyd
gmms/CampbellBozorgnia2011_cy.pyx
gmms/CampbellBozorgnia2011_py.py
gmms/CampbellBozorgnia2014.py
gmms/CampbellBozorgnia2014_cy.c
gmms/CampbellBozorgnia2014_cy.cp312-win_amd64.pyd
gmms/CampbellBozorgnia2014_cy.pyx
gmms/CampbellBozorgnia2014_py.py
gmms/CampbellBozorgnia2019.py
gmms/CampbellBozorgnia2019_cy.c
gmms/CampbellBozorgnia2019_cy.cp312-win_amd64.pyd
gmms/CampbellBozorgnia2019_cy.pyx
gmms/CampbellBozorgnia2019_py.py
gmms/FoulserPiggottGoda2015.py
gmms/FoulserPiggottGoda2015_cy.c
gmms/FoulserPiggottGoda2015_cy.cp312-win_amd64.pyd
gmms/FoulserPiggottGoda2015_cy.pyx
gmms/FoulserPiggottGoda2015_py.py
gmms/__init__.py
gmms/distancetools.py
gmms/distancetools_cy.c
gmms/distancetools_cy.cp312-win_amd64.pyd
gmms/distancetools_cy.pyx
gmms/distancetools_py.py
gmms/faulttools.py
gmms-0.2.0.dist-info/licenses/LICENSE
gmms-0.2.0.dist-info/METADATA
gmms-0.2.0.dist-info/WHEEL
gmms-0.2.0.dist-info/top_level.txt
gmms-0.2.0.dist-info/RECORD
