Metadata-Version: 2.4
Name: gmms
Version: 0.2.0
Summary: Ground motion models and supporting tools.
Home-page: https://github.com/RPretellD/gmms
Author: A. Renmin Pretell Ductram
Author-email: rpretell@unr.edu
License-Expression: MIT
Keywords: gmms
Classifier: Programming Language :: Python
Classifier: Programming Language :: Cython
Classifier: Programming Language :: Python :: 3
Requires-Python: >=3.7
License-File: LICENSE
Requires-Dist: numpy
Requires-Dist: Cython
Requires-Dist: geopy
Requires-Dist: shapely
Requires-Dist: nvector
Requires-Dist: vincenty
Dynamic: author-email
Dynamic: home-page
Dynamic: license-file
Dynamic: requires-python
